{"running_config": {"initial_module": "classifier_video_11", "initial_function": "train"}, "graph_config": [{"shape": "edge", "attrs": {"line": {"stroke": "#A2B1C3", "targetMarker": {"name": "block", "width": 12, "height": 8}}}, "id": "07420f09-97d5-4c9c-96fd-c6657a6d7034", "zIndex": 0, "source": {"cell": "6043b740-59f5-4c71-bffe-0ddb0fb254bf", "port": "ca43170b-e99c-4b68-b0c3-67bf0f4a911d"}, "target": {"cell": "353481b7-2baf-42b9-a691-c2f2e60eedd6", "port": "f76ddb7a-4117-4d8c-8fc5-d379d9240d8f"}, "data": {"link_func": "set_data_source"}}, {"shape": "edge", "attrs": {"line": {"stroke": "#A2B1C3", "targetMarker": {"name": "block", "width": 12, "height": 8}}}, "id": "95187991-87b0-4507-8ee3-91969d3f54c5", "zIndex": 0, "source": {"cell": "353481b7-2baf-42b9-a691-c2f2e60eedd6", "port": "dbfd3cb1-47b1-42a5-9acd-5f12b6c0e5d3"}, "target": {"cell": "bd1647e2-78e2-4076-9b47-88f7f4352e57", "port": "a462f543-84ed-4592-996a-187ea736a7ad"}, "data": {"link_func": "set_feature_extractor"}}, {"position": {"x": 0, "y": 571}, "size": {"width": 80, "height": 34.285714285714285}, "attrs": {"body": {"fill": "#fed330"}, "label": {"textWrap": {"text": "datasource_video_9"}}}, "shape": "Datasource", "ports": {"groups": {"top": {"position": "top", "attrs": {"circle": {"r": 4, "magnet": true, "stroke": "#5F95FF", "strokeWidth": 1, "fill": "#fff", "style": {"visibility": "hidden"}}}}, "right": {"position": "right", "attrs": {"circle": {"r": 4, "magnet": true, "stroke": "#5F95FF", "strokeWidth": 1, "fill": "#fff", "style": {"visibility": "hidden"}}}}, "bottom": {"position": "bottom", "attrs": {"circle": {"r": 4, "magnet": true, "stroke": "#5F95FF", "strokeWidth": 1, "fill": "#fff", "style": {"visibility": "hidden"}}}}, "left": {"position": "left", "attrs": {"circle": {"r": 4, "magnet": true, "stroke": "#5F95FF", "strokeWidth": 1, "fill": "#fff", "style": {"visibility": "hidden"}}}}}, "items": [{"group": "top", "id": "6062947d-8174-468c-a064-eccc47127ddc"}, {"group": "right", "id": "ca43170b-e99c-4b68-b0c3-67bf0f4a911d"}, {"group": "bottom", "id": "554182a9-c365-4276-84a9-b1adf23cbf93"}, {"group": "left", "id": "abcd2eae-ee3f-418d-953f-6b1469fc62be"}]}, "id": "6043b740-59f5-4c71-bffe-0ddb0fb254bf", "data": {"name": "datasource_video", "layer": "3", "learning_rate": "0.013", "local_name": "datasource_video_9"}, "zIndex": 2}, {"position": {"x": 126, "y": 571}, "size": {"width": 80, "height": 34.285714285714285}, "attrs": {"body": {"fill": "#26de81"}, "label": {"textWrap": {"text": "feature_extractor_video_10"}}}, "shape": "Feature_extrator", "ports": {"groups": {"top": {"position": "top", "attrs": {"circle": {"r": 4, "magnet": true, "stroke": "#5F95FF", "strokeWidth": 1, "fill": "#fff", "style": {"visibility": "hidden"}}}}, "right": {"position": "right", "attrs": {"circle": {"r": 4, "magnet": true, "stroke": "#5F95FF", "strokeWidth": 1, "fill": "#fff", "style": {"visibility": "hidden"}}}}, "bottom": {"position": "bottom", "attrs": {"circle": {"r": 4, "magnet": true, "stroke": "#5F95FF", "strokeWidth": 1, "fill": "#fff", "style": {"visibility": "hidden"}}}}, "left": {"position": "left", "attrs": {"circle": {"r": 4, "magnet": true, "stroke": "#5F95FF", "strokeWidth": 1, "fill": "#fff", "style": {"visibility": "hidden"}}}}}, "items": [{"group": "top", "id": "5772276d-39b2-4950-8732-70b7a7b0e3ac"}, {"group": "right", "id": "dbfd3cb1-47b1-42a5-9acd-5f12b6c0e5d3"}, {"group": "bottom", "id": "aafa3f58-f67c-41f8-a429-1a114adb68b5"}, {"group": "left", "id": "f76ddb7a-4117-4d8c-8fc5-d379d9240d8f"}]}, "id": "353481b7-2baf-42b9-a691-c2f2e60eedd6", "data": {"layer": "10", "learning_rate": "0.05", "model": "feature_extractor_1.pth", "name": "feature_extractor_video", "local_name": "feature_extractor_video_10"}, "zIndex": 3}, {"position": {"x": 240, "y": 571}, "size": {"width": 80, "height": 34.285714285714285}, "attrs": {"body": {"fill": "#f8c291"}, "label": {"textWrap": {"text": "classifier_video_11"}}}, "shape": "Classifier", "ports": {"groups": {"top": {"position": "top", "attrs": {"circle": {"r": 4, "magnet": true, "stroke": "#5F95FF", "strokeWidth": 1, "fill": "#fff", "style": {"visibility": "hidden"}}}}, "right": {"position": "right", "attrs": {"circle": {"r": 4, "magnet": true, "stroke": "#5F95FF", "strokeWidth": 1, "fill": "#fff", "style": {"visibility": "hidden"}}}}, "bottom": {"position": "bottom", "attrs": {"circle": {"r": 4, "magnet": true, "stroke": "#5F95FF", "strokeWidth": 1, "fill": "#fff", "style": {"visibility": "hidden"}}}}, "left": {"position": "left", "attrs": {"circle": {"r": 4, "magnet": true, "stroke": "#5F95FF", "strokeWidth": 1, "fill": "#fff", "style": {"visibility": "hidden"}}}}}, "items": [{"group": "top", "id": "c49e75af-b10d-4d2e-bd87-bc690278856b"}, {"group": "right", "id": "2979b5d5-3ce4-437c-8029-0cd8c210efb9"}, {"group": "bottom", "id": "125499f3-0ca5-43dc-9882-40e46bcedf3a"}, {"group": "left", "id": "a462f543-84ed-4592-996a-187ea736a7ad"}]}, "id": "bd1647e2-78e2-4076-9b47-88f7f4352e57", "data": {"layer": "3", "learning_rate": "0.01", "epoch": "2", "model": "classifier_1.pth", "name": "classifier_video", "local_name": "classifier_video_11"}, "zIndex": 4}], "counter": 11}